openstoxlify/__init__.py
openstoxlify/context.py
openstoxlify/draw.py
openstoxlify/models/__init__.py
openstoxlify/models/contract.py
openstoxlify/models/enum.py
openstoxlify/models/model.py
openstoxlify/models/output.py
openstoxlify/models/series.py
openstoxlify/providers/__init__.py
openstoxlify/providers/stoxlify/__init__.py
openstoxlify/providers/stoxlify/provider.py
openstoxlify/providers/stoxlify/proto/__init__.py
openstoxlify/providers/stoxlify/proto/client.py
openstoxlify/providers/stoxlify/proto/broker/broker.proto
openstoxlify/providers/stoxlify/proto/broker/broker_pb2.py
openstoxlify/providers/stoxlify/proto/broker/broker_pb2_grpc.py
openstoxlify/providers/stoxlify/proto/market/__init__.py
openstoxlify/providers/stoxlify/proto/market/market.proto
openstoxlify/providers/stoxlify/proto/market/market_pb2.py
openstoxlify/providers/stoxlify/proto/market/market_pb2_grpc.py
openstoxlify/providers/stoxlify/proto/model/model.proto
openstoxlify/providers/stoxlify/proto/model/model_pb2.py
openstoxlify/providers/stoxlify/proto/model/model_pb2_grpc.py
openstoxlify/providers/stoxlify/proto/statistic/statistic.proto
openstoxlify/providers/stoxlify/proto/statistic/statistic_pb2.py
openstoxlify/providers/stoxlify/proto/statistic/statistic_pb2_grpc.py
openstoxlify/providers/stoxlify/proto/trade/trade.proto
openstoxlify/providers/stoxlify/proto/trade/trade_pb2.py
openstoxlify/providers/stoxlify/proto/trade/trade_pb2_grpc.py
openstoxlify/providers/stoxlify/proto/types/amount/amount.proto
openstoxlify/providers/stoxlify/proto/types/amount/amount_pb2.py
openstoxlify/providers/stoxlify/proto/types/amount/amount_pb2_grpc.py
openstoxlify/utils/__init__.py
openstoxlify/utils/color.py
openstoxlify/utils/output.py
openstoxlify/utils/period.py
openstoxlify/utils/time.py
openstoxlify/utils/token.py
openstoxlify-1.3.1.dist-info/licenses/LICENSE
openstoxlify-1.3.1.dist-info/METADATA
openstoxlify-1.3.1.dist-info/WHEEL
openstoxlify-1.3.1.dist-info/top_level.txt
openstoxlify-1.3.1.dist-info/RECORD
