Metadata-Version: 2.4
Name: openstoxlify
Version: 1.3.1
Summary: A lightweight Python library for algorithmic trading and market analysis
Author-email: Stoxlify <mail.stoxlify@gmail.com>
License: MIT
Project-URL: Homepage, https://github.com/michaelahli/openstoxlify
Project-URL: Repository, https://github.com/michaelahli/openstoxlify
Keywords: trading,finance,algorithmic-trading,technical-analysis
Requires-Python: >=3.8
License-File: LICENSE
Requires-Dist: requests>=2.25.0
Requires-Dist: matplotlib>=3.5.0
Requires-Dist: grpcio
Requires-Dist: protobuf
Requires-Dist: utcnow
Provides-Extra: dev
Requires-Dist: pytest>=7.0.0; extra == "dev"
Requires-Dist: pytest-cov>=4.0.0; extra == "dev"
Requires-Dist: pytest-mock>=3.10.0; extra == "dev"
Requires-Dist: twine>=4.0.0; extra == "dev"
Requires-Dist: build>=0.10.0; extra == "dev"
Dynamic: license-file
